reactpy_django/__init__.py
reactpy_django/apps.py
reactpy_django/checks.py
reactpy_django/components.py
reactpy_django/config.py
reactpy_django/database.py
reactpy_django/decorators.py
reactpy_django/exceptions.py
reactpy_django/hooks.py
reactpy_django/html.py
reactpy_django/javascript_components.py
reactpy_django/models.py
reactpy_django/py.typed
reactpy_django/tasks.py
reactpy_django/types.py
reactpy_django/utils.py
reactpy_django/auth/__init__.py
reactpy_django/auth/components.py
reactpy_django/forms/__init__.py
reactpy_django/forms/components.py
reactpy_django/forms/transforms.py
reactpy_django/forms/utils.py
reactpy_django/http/__init__.py
reactpy_django/http/urls.py
reactpy_django/http/views.py
reactpy_django/management/__init__.py
reactpy_django/management/commands/__init__.py
reactpy_django/management/commands/clean_reactpy.py
reactpy_django/migrations/0001_initial.py
reactpy_django/migrations/0002_rename_created_at_componentparams_last_accessed.py
reactpy_django/migrations/0003_componentsession_delete_componentparams.py
reactpy_django/migrations/0004_config.py
reactpy_django/migrations/0005_alter_componentsession_last_accessed.py
reactpy_django/migrations/0006_userdatamodel.py
reactpy_django/migrations/0007_authtoken.py
reactpy_django/migrations/__init__.py
reactpy_django/pyscript/__init__.py
reactpy_django/pyscript/component_template.py
reactpy_django/pyscript/components.py
reactpy_django/pyscript/layout_handler.py
reactpy_django/pyscript/utils.py
reactpy_django/router/__init__.py
reactpy_django/router/converters.py
reactpy_django/router/resolvers.py
reactpy_django/static/reactpy_django/client.js
reactpy_django/static/reactpy_django/pyscript-custom.css
reactpy_django/static/reactpy_django/pyscript-hide-debug.css
reactpy_django/static/reactpy_django/morphdom/morphdom-esm.js
reactpy_django/static/reactpy_django/morphdom/morphdom-factory.js
reactpy_django/static/reactpy_django/morphdom/morphdom-umd.js
reactpy_django-5.2.1.dist-info/METADATA
reactpy_django-5.2.1.dist-info/WHEEL
reactpy_django-5.2.1.dist-info/licenses/LICENSE.md
reactpy_django-5.2.1.dist-info/RECORD
