Metadata-Version: 2.4
Name: reactpy_django
Version: 5.2.1
Summary: It's React, but in Python. Now with Django integration.
Project-URL: Changelog, https://reactive-python.github.io/reactpy-django/latest/about/changelog/
Project-URL: Documentation, https://reactive-python.github.io/reactpy-django/
Project-URL: Source, https://github.com/reactive-python/reactpy-django
Author-email: Mark Bakhit <archiethemonger@gmail.com>
License-Expression: MIT
License-File: LICENSE.md
Keywords: React,ReactJS,ReactPy,asgi,components,django,http,interactive,reactive,server
Classifier: Environment :: Web Environment
Classifier: Framework :: Django
Classifier: Framework :: Django :: 4.0
Classifier: Intended Audience :: Developers
Classifier: Intended Audience :: Science/Research
Classifier: Operating System :: OS Independent
Classifier: Programming Language :: Python :: 3.9
Classifier: Programming Language :: Python :: 3.10
Classifier: Programming Language :: Python :: 3.11
Classifier: Programming Language :: Python :: 3.12
Classifier: Topic :: Multimedia :: Graphics
Classifier: Topic :: Software Development :: User Interfaces
Classifier: Topic :: Software Development :: Widget Sets
Classifier: Typing :: Typed
Requires-Python: >=3.9
Requires-Dist: channels>=4.0.0
Requires-Dist: dill>=0.3.5
Requires-Dist: django>=4.2.0
Requires-Dist: nest-asyncio>=1.5.0
Requires-Dist: orjson>=3.6.0
Requires-Dist: reactpy-router<2.0.0,>=1.0.3
Requires-Dist: reactpy<2.0.0,>=1.1.0
Requires-Dist: typing-extensions
